seeme/__init__.py
seeme/documents.py
seeme/helpers.py
seeme/ollama.py
seeme/search.py
seeme/seeme_client.py
seeme/types.py
seeme/version.py
seeme/vllm.py
seeme-0.40.0.dist-info/METADATA
seeme-0.40.0.dist-info/WHEEL
seeme-0.40.0.dist-info/top_level.txt
seeme-0.40.0.dist-info/RECORD
