Metadata-Version: 2.4
Name: seeme
Version: 0.40.0
Summary: No-Code/Low Code AI Platform: Innovate. Integrate. Iterate.
Home-page: https://seeme.ai
Author: Jan Van de Poel
Author-email: jan.vandepoel@seeme.ai
License: Apache
Classifier: Development Status :: 5 - Production/Stable
Classifier: Intended Audience :: Developers
Classifier: Intended Audience :: Education
Classifier: Intended Audience :: Science/Research
Classifier: License :: OSI Approved :: Apache Software License
Classifier: Operating System :: OS Independent
Classifier: Programming Language :: Python :: 3
Classifier: Programming Language :: Python :: 3 :: Only
Classifier: Programming Language :: Python :: 3.7
Classifier: Programming Language :: Python :: 3.8
Classifier: Programming Language :: Python :: 3.9
Classifier: Programming Language :: Python :: 3.10
Classifier: Programming Language :: Python :: 3.11
Classifier: Topic :: Scientific/Engineering :: Artificial Intelligence
Requires-Python: >=3.7.0
Requires-Dist: requests>=2.18.4
Requires-Dist: requests-toolbelt==0.10.1
Requires-Dist: python-dotenv
Requires-Dist: pydantic<3.0.0,>=2.0.0
Requires-Dist: urllib3==1.26.15
Requires-Dist: pandas
Provides-Extra: storage
Requires-Dist: dill; extra == "storage"
Provides-Extra: search
Requires-Dist: bm25s; extra == "search"
Requires-Dist: numba; extra == "search"
Provides-Extra: documents
Requires-Dist: pypdf; extra == "documents"
Requires-Dist: python-docx; extra == "documents"
Requires-Dist: pycryptodome; extra == "documents"
Requires-Dist: nltk; extra == "documents"
Requires-Dist: sentence-transformers; extra == "documents"
Provides-Extra: ollama
Requires-Dist: ollama; extra == "ollama"
Requires-Dist: instructor; extra == "ollama"
Provides-Extra: vllm
Requires-Dist: vllm; extra == "vllm"
Provides-Extra: web
Requires-Dist: beautifulsoup4; extra == "web"
Provides-Extra: all
Requires-Dist: dill; extra == "all"
Requires-Dist: bm25s; extra == "all"
Requires-Dist: pypdf; extra == "all"
Requires-Dist: python-docx; extra == "all"
Requires-Dist: pycryptodome; extra == "all"
Requires-Dist: ollama; extra == "all"
Requires-Dist: instructor; extra == "all"
Requires-Dist: vllm; extra == "all"
Requires-Dist: nltk; extra == "all"
Requires-Dist: beautifulsoup4; extra == "all"
Requires-Dist: sentence-transformers; extra == "all"
Dynamic: author
Dynamic: author-email
Dynamic: classifier
Dynamic: description
Dynamic: description-content-type
Dynamic: home-page
Dynamic: license
Dynamic: provides-extra
Dynamic: requires-dist
Dynamic: requires-python
Dynamic: summary
